pasek/__init__.py
pasek/pasek.py
pasek-1.0.0.dist-info/METADATA
pasek-1.0.0.dist-info/WHEEL
pasek-1.0.0.dist-info/top_level.txt
pasek-1.0.0.dist-info/RECORD
